PyBarst-2.1.data/data/share/pybarst/bin/barst64.exe
PyBarst-2.1.data/data/share/pybarst/bin/cbw64.dll
PyBarst-2.1.dist-info/DESCRIPTION.rst
PyBarst-2.1.dist-info/METADATA
PyBarst-2.1.dist-info/RECORD
PyBarst-2.1.dist-info/WHEEL
PyBarst-2.1.dist-info/metadata.json
PyBarst-2.1.dist-info/top_level.txt
pybarst/__init__.py
pybarst/core/__init__.py
pybarst/core/exception.pyd
pybarst/core/server.pyd
pybarst/ftdi/__init__.py
pybarst/ftdi/_ftdi.pyd
pybarst/ftdi/adc.pyd
pybarst/ftdi/switch.pyd
pybarst/mcdaq/__init__.py
pybarst/mcdaq/_mcdaq.pyd
pybarst/rtv/__init__.py
pybarst/rtv/_rtv.pyd
pybarst/serial/__init__.py
pybarst/serial/_serial.pyd
