Metadata-Version: 2.0
Name: PyBarst
Version: 2.1
Summary: An interface to Barst.
Home-page: http://matham.github.io/pybarst/
Author: Matthew Einhorn
Author-email: moiein2000@gmail.com
License: MIT
Platform: UNKNOWN
Classifier: License :: OSI Approved :: MIT License
Classifier: Topic :: Scientific/Engineering
Classifier: Topic :: System :: Hardware
Classifier: Programming Language :: Python :: 2.7
Classifier: Programming Language :: Python :: 3.3
Classifier: Programming Language :: Python :: 3.4
Classifier: Programming Language :: Python :: 3.5
Classifier: Operating System :: Microsoft :: Windows
Classifier: Intended Audience :: Developers
